pailliers/__init__.py
pailliers/pailliers.py
pailliers-0.1.0.dist-info/LICENSE
pailliers-0.1.0.dist-info/METADATA
pailliers-0.1.0.dist-info/WHEEL
pailliers-0.1.0.dist-info/top_level.txt
pailliers-0.1.0.dist-info/RECORD
